setup.py
lawliet/__init__.py
lawliet/app.py
lawliet/request.py
lawliet.egg-info/PKG-INFO
lawliet.egg-info/SOURCES.txt
lawliet.egg-info/dependency_links.txt
lawliet.egg-info/not-zip-safe
lawliet.egg-info/top_level.txt