Metadata-Version: 1.1
Name: lawliet
Version: 2.1.0
Summary: a web framework
Home-page: https://github.com/fing520/Lawliet
Author: Monomer Xu
Author-email: fing@easymail.com.cn
License: MIT
Platform: any
Classifier: Environment :: Web Environment
Classifier: Intended Audience :: Developers
Classifier: License :: OSI Approved :: MIT License
Classifier: Operating System :: OS Independent
Classifier: Programming Language :: Python
Classifier: Topic :: Internet :: WWW/HTTP :: Dynamic Content
Classifier: Topic :: Software Development :: Libraries :: Python Modules
